libimobiledevice_wrapper/__init__.py
libimobiledevice_wrapper/cli.py
libimobiledevice_wrapper/core.py
libimobiledevice_wrapper/tests.py
libimobiledevice_wrapper/utils.py
libimobiledevice_wrapper/webdriveragent.py
libimobiledevice_wrapper-1.1.0.dist-info/licenses/LICENSE
libimobiledevice_wrapper-1.1.0.dist-info/METADATA
libimobiledevice_wrapper-1.1.0.dist-info/WHEEL
libimobiledevice_wrapper-1.1.0.dist-info/entry_points.txt
libimobiledevice_wrapper-1.1.0.dist-info/top_level.txt
libimobiledevice_wrapper-1.1.0.dist-info/RECORD
