Metadata-Version: 2.4
Name: libimobiledevice-wrapper
Version: 1.1.0
Summary: Python wrapper for libimobiledevice with async support and CLI tools
Author-email: Huang-Jacky <hjc853@gmail.com>
License: MIT
Project-URL: Homepage, https://github.com/Huang-Jacky/libimobiledevice-wrapper
Project-URL: Repository, https://github.com/Huang-Jacky/libimobiledevice-wrapper
Project-URL: Issues, https://github.com/Huang-Jacky/libimobiledevice-wrapper/issues
Keywords: ios,libimobiledevice,mobile,automation,testing
Classifier: Development Status :: 4 - Beta
Classifier: Intended Audience :: Developers
Classifier: License :: OSI Approved :: MIT License
Classifier: Programming Language :: Python :: 3
Classifier: Programming Language :: Python :: 3.8
Classifier: Programming Language :: Python :: 3.9
Classifier: Programming Language :: Python :: 3.10
Classifier: Programming Language :: Python :: 3.11
Classifier: Programming Language :: Python :: 3.12
Classifier: Topic :: Software Development :: Testing
Classifier: Topic :: System :: Hardware
Requires-Python: >=3.8
License-File: LICENSE
Requires-Dist: click>=8.0.0
Requires-Dist: aiofiles>=23.0.0
Requires-Dist: rich>=13.0.0
Requires-Dist: aiohttp>=3.8.0
Provides-Extra: dev
Requires-Dist: pytest>=7.0.0; extra == "dev"
Requires-Dist: pytest-asyncio>=0.21.0; extra == "dev"
Requires-Dist: black>=23.0.0; extra == "dev"
Requires-Dist: flake8>=6.0.0; extra == "dev"
Requires-Dist: mypy>=1.0.0; extra == "dev"
Dynamic: license-file
